{"name":"Julio César Green","record":[{"no":"34","result":"Win","record":"27–6–1","opponent":" Filberto Alvarez","type":"TKO","roundTime":"2 (6)","date":"Sep 03, 2004","age":null,"location":" Club R.P. Acevedo, Santo Domingo ","notes":""},{"no":"33","result":"Loss","record":"26–6–1","opponent":" Mikkel Kessler","type":"KO","roundTime":"1 (12)","date":"Mar 13, 2004","age":null,"location":" Brøndby Hall, Copenhagen, Denmark","notes":"For WBC International super-middleweight title"},{"no":"32","result":"Win","record":"26–5–1","opponent":" Roberto Jimenez","type":"KO","roundTime":"1 (?)","date":"Jan 05, 2004","age":null,"location":" Acropolis Disco, Santiago de los Caballeros ","notes":""},{"no":"31","result":"Loss","record":"25–5–1","opponent":" Byron Mitchell","type":"TKO","roundTime":"4 (12)","date":"Jul 27, 2002","age":null,"location":" Mandalay Bay Resort & Casino, Las Vegas  ","notes":"For WBA super-middleweight title"},{"no":"30","result":"Draw","record":"25–4–1","opponent":" Charles Whittaker","type":"PTS","roundTime":"8","date":"May 12, 2001","age":null,"location":" Madison Square Garden, New York ","notes":""},{"no":"29","result":"Loss","record":"25–4","opponent":" William Joppy","type":"TKO","roundTime":"7 (12)","date":"Sep 24, 1999","age":null,"location":" MCI Center, Washington  ","notes":"For WBA middleweight title"},{"no":"28","result":"Win","record":"25–3","opponent":" Jerry Williams","type":"UD","roundTime":"10","date":"May 15, 1999","age":null,"location":" Jai Alai Fronton, Miami ","notes":""},{"no":"27","result":"Win","record":"24–3","opponent":" Darren Obah","type":"TKO","roundTime":"9 (12)","date":"Feb 20, 1999","age":null,"location":" Madison Square Garden, New York ","notes":""},{"no":"26","result":"Win","record":"23–3","opponent":" Joaquin Velasquez","type":"TKO","roundTime":"6 (10)","date":"Aug 28, 1998","age":null,"location":" Las Vegas Hilton, Las Vegas ","notes":""},{"no":"25","result":"Loss","record":"22–3","opponent":" William Joppy","type":"UD","roundTime":"12","date":"Jan 31, 1998","age":null,"location":" Ice Palace, Tampa ","notes":"Lost WBA middleweight title"},{"no":"24","result":"Win","record":"22–2","opponent":" William Joppy","type":"UD","roundTime":"12","date":"Aug 23, 1997","age":null,"location":" Madison Square Garden, New York ","notes":"Won WBA middleweight title"},{"no":"23","result":"Win","record":"21–2","opponent":" Earl Allen","type":"TKO","roundTime":"9 (10)","date":"Jun 21, 1997","age":null,"location":" Sun Dome, Tampa ","notes":""},{"no":"22","result":"Win","record":"20–2","opponent":" Bernice Barber","type":"KO","roundTime":"4 (8)","date":"Mar 29, 1997","age":null,"location":" Hilton Hotel, Las Vegas ","notes":""},{"no":"21","result":"Loss","record":"19–2","opponent":" Carl Daniels","type":"UD","roundTime":"12","date":"Jun 16, 1995","age":null,"location":" Palais des Sports de Gerland, Lyon ","notes":"For vacant WBA super welterweight title"},{"no":"20","result":"Win","record":"19–1","opponent":" Bill Bradley","type":"TKO","roundTime":"1 (10)","date":"Jan 28, 1995","age":null,"location":" Ballys Park Place Hotel Casino, Atlantic City ","notes":""},{"no":"19","result":"Win","record":"18–1","opponent":" Kevin Tillman","type":"TKO","roundTime":"5 (10)","date":"Jun 12, 1994","age":null,"location":" Trump Plaza Hotel, Atlantic City ","notes":""},{"no":"18","result":"Win","record":"17–1","opponent":" Lonnie Beasley","type":"TKO","roundTime":"12 (12)","date":"Apr 19, 1994","age":null,"location":" Caesars Palace, Las Vegas ","notes":""},{"no":"17","result":"Win","record":"16–1","opponent":" Matthew Charleston","type":"TKO","roundTime":"1 (10)","date":"Feb 12, 1994","age":null,"location":" Cervantes Center, Saint Louis ","notes":""},{"no":"16","result":"Win","record":"15–1","opponent":" Wayne Powell","type":"TKO","roundTime":"7 (12)","date":"Oct 23, 1993","age":null,"location":" Sands Casino Hotel, Atlantic City ","notes":""},{"no":"15","result":"Win","record":"14–1","opponent":" James Gatlin","type":"TKO","roundTime":"1 (10)","date":"Oct 01, 1993","age":null,"location":" Ramada Hotel, New York ","notes":""},{"no":"14","result":"Win","record":"13–1","opponent":" Ricky Thomas","type":"TKO","roundTime":"5 (10)","date":"Jul 08, 1993","age":null,"location":" Paramount Theatre, New York  ","notes":""},{"no":"13","result":"Win","record":"12–1","opponent":" Eric Holland","type":"UD","roundTime":"10","date":"Feb 18, 1993","age":null,"location":" Paramount Theatre, New York  ","notes":""},{"no":"12","result":"Win","record":"11–1","opponent":" Willie Douglas","type":"TKO","roundTime":"8 (10)","date":"Nov 20, 1992","age":null,"location":" Ramada Hotel, New York ","notes":""},{"no":"11","result":"Win","record":"10–1","opponent":" Oscar Noriega","type":"TKO","roundTime":"2 (8)","date":"Oct 15, 1992","age":null,"location":" Paramount Theatre, New York ","notes":""},{"no":"10","result":"Win","record":"9–1","opponent":" William Bo James","type":"MD","roundTime":"8","date":"Sep 17, 1992","age":null,"location":" Paramount Theatre, New York ","notes":""},{"no":"9","result":"Win","record":"8–1","opponent":" Kevin Prather","type":"MD","roundTime":"6","date":"Jul 24, 1992","age":null,"location":" Friar Tuck Inn, Catskill ","notes":""},{"no":"8","result":"Win","record":"7–1","opponent":" Kilpatrick Mitchell","type":"PTS","roundTime":"6","date":"Jul 16, 1992","age":null,"location":" Taj Majal Hotel & Casino, Atlantic City ","notes":""},{"no":"7","result":"Win","record":"6–1","opponent":" Ron Woodley","type":"UD","roundTime":"6","date":"Feb 18, 1992","age":null,"location":" Paramount Theatre, New York ","notes":""},{"no":"6","result":"Win","record":"5–1","opponent":" Aureliano Sosa","type":"KO","roundTime":"1 (6)","date":"Jan 10, 1992","age":null,"location":" Paramount Theatre, New York ","notes":""},{"no":"5","result":"Loss","record":"4–1","opponent":" Kevin Tillman","type":"PTS","roundTime":"6","date":"Sep 27, 1991","age":null,"location":" Blue Horizon, Philadelphia  ","notes":""},{"no":"4","result":"Win","record":"4–0","opponent":" Ricky Rucker","type":"KO","roundTime":"3 (4)","date":"Feb 09, 1991","age":null,"location":" Meadowlands Convention Center, Secaucus ","notes":""},{"no":"3","result":"Win","record":"3–0","opponent":" Garfield McKenzie","type":"TKO","roundTime":"1 (?)","date":"Feb 09, 1991","age":null,"location":" Madison Square Garden, New York ","notes":""},{"no":"2","result":"Win","record":"2–0","opponent":" Drew Hayes","type":"PTS","roundTime":"4","date":"Jan 19, 1991","age":null,"location":" Convention Center, Atlantic City ","notes":""},{"no":"1","result":"Win","record":"1–0","opponent":" Bill Robinson","type":"TKO","roundTime":"2 (?)","date":"Oct 30, 1990","age":null,"location":" Pines Hotel, South Fallsburg ","notes":""}]}